LICENSE
MANIFEST.in
README.md
setup.cfg
setup.py
avryp/__init__.py
avryp.egg-info/PKG-INFO
avryp.egg-info/SOURCES.txt
avryp.egg-info/dependency_links.txt
avryp.egg-info/requires.txt
avryp.egg-info/top_level.txt
avryp.egg-info/zip-safe
examples/blink/blink.py
examples/blink/blink_vars.py
examples/blink_c/blink.c
examples/blink_c/compile.py
examples/blink_c/dt.c
examples/usb/mouse/compil.py
examples/usb/mouse/main.c
examples/usb/mouse/usbdrv/oddebug.c
examples/usb/mouse/usbdrv/oddebug.h
examples/usb/mouse/usbdrv/usbconfig-prototype.h
examples/usb/mouse/usbdrv/usbconfig.h
examples/usb/mouse/usbdrv/usbdrv.c
examples/usb/mouse/usbdrv/usbdrv.h
examples/usb/mouse/usbdrv/usbdrvasm.S
examples/usb/mouse/usbdrv/usbportability.h