Metadata-Version: 1.1
Name: avryp
Version: 0.0.9
Summary: Avryp is a Python package to build and flash AVR and Arduino code.
Home-page: https://github.com/tovam/avryp
Author: tovam
Author-email: tovamdvlp@gmail.com
License: MIT
Keywords: avr arduino atmel
Platform: UNKNOWN
Classifier: License :: OSI Approved :: MIT License
Classifier: Natural Language :: English
Classifier: Operating System :: OS Independent
Classifier: Programming Language :: Python
Classifier: Programming Language :: Python :: 2
Classifier: Programming Language :: Python :: 3
Classifier: Topic :: Software Development
